atoma_sdk/__init__.py
atoma_sdk/_hooks/__init__.py
atoma_sdk/_hooks/registration.py
atoma_sdk/_hooks/sdkhooks.py
atoma_sdk/_hooks/types.py
atoma_sdk/_version.py
atoma_sdk/basesdk.py
atoma_sdk/chat.py
atoma_sdk/confidential_chat.py
atoma_sdk/confidential_embeddings.py
atoma_sdk/confidential_images.py
atoma_sdk/crypto_utils.py
atoma_sdk/embeddings.py
atoma_sdk/health.py
atoma_sdk/httpclient.py
atoma_sdk/images.py
atoma_sdk/models/__init__.py
atoma_sdk/models/apierror.py
atoma_sdk/models/chatcompletionchoice.py
atoma_sdk/models/chatcompletionchunk.py
atoma_sdk/models/chatcompletionchunkchoice.py
atoma_sdk/models/chatcompletionchunkdelta.py
atoma_sdk/models/chatcompletionmessage.py
atoma_sdk/models/chatcompletionresponse.py
atoma_sdk/models/chatcompletionstreamresponse.py
atoma_sdk/models/completionusage.py
atoma_sdk/models/confidentialcomputerequest.py
atoma_sdk/models/confidentialcomputeresponse.py
atoma_sdk/models/confidentialcomputestreamresponse.py
atoma_sdk/models/createchatcompletionrequest.py
atoma_sdk/models/createchatcompletionstreamrequest.py
atoma_sdk/models/createembeddingrequest.py
atoma_sdk/models/createembeddingresponse.py
atoma_sdk/models/createimagerequest.py
atoma_sdk/models/createimageresponse.py
atoma_sdk/models/embeddinginput.py
atoma_sdk/models/embeddingobject.py
atoma_sdk/models/embeddingusage.py
atoma_sdk/models/healthresponse.py
atoma_sdk/models/imagedata.py
atoma_sdk/models/model.py
atoma_sdk/models/modellist.py
atoma_sdk/models/nodepublicaddressassignment.py
atoma_sdk/models/nodescreatelockrequest.py
atoma_sdk/models/nodescreatelockresponse.py
atoma_sdk/models/nodescreaterequest.py
atoma_sdk/models/nodescreateresponse.py
atoma_sdk/models/security.py
atoma_sdk/models/usage.py
atoma_sdk/models_.py
atoma_sdk/nodes.py
atoma_sdk/py.typed
atoma_sdk/sdk.py
atoma_sdk/sdkconfiguration.py
atoma_sdk/types/__init__.py
atoma_sdk/types/basemodel.py
atoma_sdk/utils/__init__.py
atoma_sdk/utils/annotations.py
atoma_sdk/utils/enums.py
atoma_sdk-0.1.3.dist-info/LICENSE
atoma_sdk-0.1.3.dist-info/METADATA
atoma_sdk-0.1.3.dist-info/WHEEL
atoma_sdk-0.1.3.dist-info/RECORD
