Metadata-Version: 2.3
Name: atoma-sdk
Version: 0.1.3
Summary: Python Client SDK Generated by Speakeasy.
Author: Speakeasy
Requires-Python: >=3.8, !=2.7.*, !=3.0.*, !=3.1.*, !=3.2.*, !=3.3.*, !=3.4.*, !=3.5.*, !=3.6.*, !=3.7.*
Classifier: Programming Language :: Python :: 3
Classifier: Programming Language :: Python :: 3.8
Classifier: Programming Language :: Python :: 3.10
Classifier: Programming Language :: Python :: 3.11
Classifier: Programming Language :: Python :: 3.12
Classifier: Programming Language :: Python :: 3.13
Requires-Dist: cryptography (>=44.0.0)
Requires-Dist: eval-type-backport (>=0.2.0,<0.3.0)
Requires-Dist: httpx (>=0.28.1,<0.29.0)
Requires-Dist: jsonpath-python (>=1.0.6,<2.0.0)
Requires-Dist: pydantic (>=2.10.3,<2.11.0)
Requires-Dist: python-dateutil (>=2.8.2,<3.0.0)
Requires-Dist: typing-inspect (>=0.9.0,<0.10.0)
Project-URL: Repository, https://github.com/atoma-network/atoma-sdk-python.git
